boileroom/__init__.py
boileroom/base.py
boileroom/constants.py
boileroom/convert.py
boileroom/utils.py
boileroom/images/__init__.py
boileroom/images/esm.py
boileroom/images/volumes.py
boileroom/models/__init__.py
boileroom/models/esm/__init__.py
boileroom/models/esm/esm2.py
boileroom/models/esm/esmfold.py
boileroom/models/esm/linker.py
boileroom-0.2.2.dist-info/METADATA
boileroom-0.2.2.dist-info/WHEEL
boileroom-0.2.2.dist-info/licenses/LICENSE
boileroom-0.2.2.dist-info/RECORD
