Metadata-Version: 2.4
Name: boileroom
Version: 0.2.2
Summary: Protein prediction models with Modal
Project-URL: Homepage, https://github.com/jakublala/boileroom
Author-email: Jakub Lála <jakublala@gmail.com>
License-File: LICENSE
Classifier: License :: OSI Approved :: MIT License
Classifier: Operating System :: OS Independent
Classifier: Programming Language :: Python :: 3
Requires-Python: >=3.11
Requires-Dist: biotite>=1.0.1
Requires-Dist: deprecated>=1.2.14
Requires-Dist: modal>=1.1.0
Requires-Dist: numpy>=2.2.2
Requires-Dist: torch<2.7.0,>=2.5.1
Provides-Extra: dev
Requires-Dist: pre-commit>=4.1.0; extra == 'dev'
Requires-Dist: pytest-mock>=3.14.0; extra == 'dev'
Requires-Dist: pytest-xdist>=3.6.1; extra == 'dev'
Requires-Dist: pytest>=8.3.4; extra == 'dev'
Provides-Extra: local
Requires-Dist: transformers>=4.49.0; extra == 'local'
